AUTHORS.rst
CONTRIBUTING.rst
HISTORY.rst
LICENSE
MANIFEST.in
README.rst
setup.cfg
setup.py
curriculum/__init__.py
curriculum/admin.py
curriculum/apps.py
curriculum/models.py
curriculum/serializers.py
curriculum/urls.py
curriculum/views.py
curriculum/migrations/0001_initial.py
curriculum/migrations/__init__.py
curriculum/static/css/django_curriculum.css
curriculum/static/js/django_curriculum.js
curriculum/templates/django_curriculum/base.html
django_curriculum.egg-info/PKG-INFO
django_curriculum.egg-info/SOURCES.txt
django_curriculum.egg-info/dependency_links.txt
django_curriculum.egg-info/not-zip-safe
django_curriculum.egg-info/top_level.txt