Metadata-Version: 1.1
Name: django-curriculum
Version: 0.1.13
Summary: A simple django project to create a curriculum vitae
Home-page: https://github.com/axeliodiaz/django-curriculum
Author: Axel Diaz
Author-email: diaz.axelio@gmail.com
License: MIT
Keywords: django-curriculum
Platform: UNKNOWN
Classifier: Development Status :: 3 - Alpha
Classifier: Framework :: Django
Classifier: Framework :: Django :: 1.10
Classifier: Intended Audience :: Developers
Classifier: License :: OSI Approved :: BSD License
Classifier: Natural Language :: English
Classifier: Programming Language :: Python :: 2
Classifier: Programming Language :: Python :: 2.7
Classifier: Programming Language :: Python :: 3
Classifier: Programming Language :: Python :: 3.4
Classifier: Programming Language :: Python :: 3.5
